dclean/__init__.py
dclean/main.py
dclean/analyze/__init__.py
dclean/analyze/analyze_add.py
dclean/analyze/analyze_cmd_entrypoint.py
dclean/analyze/analyze_container.py
dclean/analyze/analyze_from.py
dclean/analyze/analyze_run.py
dclean/analyze/main.py
dclean/api/__init__.py
dclean/api/get_repository_tags.py
dclean/utils/__init__.py
dclean/utils/get_analysis_result.py
dclean/utils/get_colored_analysis_result.py
dclean/utils/get_colored_vulnerabilities_results.py
dclean/utils/get_recommendation.py
dclean/utils/get_vulnerabilities_results.py
mist_dclean-0.1.2.dist-info/LICENSE
mist_dclean-0.1.2.dist-info/METADATA
mist_dclean-0.1.2.dist-info/WHEEL
mist_dclean-0.1.2.dist-info/entry_points.txt
mist_dclean-0.1.2.dist-info/top_level.txt
mist_dclean-0.1.2.dist-info/RECORD
