Metadata-Version: 2.2
Name: mist.dclean
Version: 0.1.2
Summary: A tool for analyzing Dockerfiles and Docker images
Home-page: https://github.com/mist941/dclean
Author: Ivan Statkevich
Author-email: statkevich.ivan@gmail.com
Project-URL: Bug Reports, https://github.com/mist941/dclean/issues
Project-URL: Source, https://github.com/mist941/dclean
Keywords: docker,optimization,cleaning,containerization,security,vulnerability,trivy
Classifier: Programming Language :: Python :: 3
Classifier: License :: OSI Approved :: MIT License
Classifier: Operating System :: OS Independent
Classifier: Development Status :: 4 - Beta
Classifier: Intended Audience :: Developers
Classifier: Intended Audience :: System Administrators
Classifier: Intended Audience :: Information Technology
Classifier: Topic :: Software Development
Classifier: Topic :: System :: Systems Administration
Requires-Python: >=3.10
License-File: LICENSE
Requires-Dist: docker<8.0.0,>=7.0.0
Requires-Dist: dockerfile-parse<3.0.0,>=2.0.0
Requires-Dist: click<9.0.0,>=8.0.0
Dynamic: author
Dynamic: author-email
Dynamic: classifier
Dynamic: description
Dynamic: description-content-type
Dynamic: home-page
Dynamic: keywords
Dynamic: project-url
Dynamic: requires-dist
Dynamic: requires-python
Dynamic: summary
